{"stats":{"minecraft:mined":{"minecraft:iron_ore":31,"minecraft:oak_log":87},"minecraft:crafted":{"minecraft:potion":2,"minecraft:arrow":5,"minecraft:bow":1,"minecraft:snowball":13,"minecraft:carrot_on_a_stick":27,"minecraft:bread":38},"minecraft:dropped":{"minecraft:bread":1,"minecraft:iron_pickaxe":1,"minecraft:emerald":6},"minecraft:used":{"minecraft:iron_axe":88,"minecraft:bread":24,"minecraft:carrot_on_a_stick":101,"minecraft:iron_pickaxe":31,"minecraft:written_book":12,"minecraft:snowball":11,"minecraft:splash_potion":1},"minecraft:killed_by":{"minecraft:player":11},"minecraft:custom":{"minecraft:time_since_rest":46694,"minecraft:sprint_one_cm":1396763,"minecraft:damage_taken":4278,"minecraft:walk_one_cm":795437,"minecraft:drop":8,"minecraft:damage_dealt":536,"minecraft:traded_with_villager":78,"minecraft:talked_to_villager":55,"minecraft:fly_one_cm":653832,"minecraft:player_kills":6,"minecraft:open_chest":1,"minecraft:crouch_one_cm":2069,"minecraft:play_time":391608,"minecraft:deaths":12,"minecraft:sneak_time":1890,"minecraft:walk_under_water_one_cm":5570,"minecraft:jump":1393,"minecraft:leave_game":18,"minecraft:walk_on_water_one_cm":13084,"minecraft:time_since_death":46582,"minecraft:climb_one_cm":1786,"minecraft:total_world_time":391608,"minecraft:fall_one_cm":25842},"minecraft:picked_up":{"minecraft:gravel":5,"minecraft:dirt":42,"minecraft:emerald":99,"minecraft:bread":17,"minecraft:iron_pickaxe":1,"minecraft:dark_oak_fence":2,"minecraft:snowball":4}},"DataVersion":3337}